sample_py/__init__.py
sample_py/_modidx.py
sample_py/core.py
rmccart_random_test-0.0.1.dist-info/LICENSE
rmccart_random_test-0.0.1.dist-info/METADATA
rmccart_random_test-0.0.1.dist-info/WHEEL
rmccart_random_test-0.0.1.dist-info/entry_points.txt
rmccart_random_test-0.0.1.dist-info/top_level.txt
rmccart_random_test-0.0.1.dist-info/RECORD
